yandexbot/__init__.py
yandexbot/bot.py
yandexbot/dependency_links.txt
yandexbot/types/__init__.py
yandexbot/types/message.py
yandexbot-0.2.3.dist-info/METADATA
yandexbot-0.2.3.dist-info/WHEEL
yandexbot-0.2.3.dist-info/RECORD
